adidasSensor/__init__.py
adidasSensor/__main__.py
adidasSensor/boot.py
adidasSensor/init.py
adidasSensor/plot.py
adidasSensor/sync.py
adidasSensor/serial/__init__.py
adidasSensor/serial/rfc2217.py
adidasSensor/serial/serialcli.py
adidasSensor/serial/serialjava.py
adidasSensor/serial/serialposix.py
adidasSensor/serial/serialutil.py
adidasSensor/serial/serialwin32.py
adidasSensor/serial/sermsdos.py
adidasSensor/serial/win32.py
adidas_sensor-1.6.dist-info/METADATA
adidas_sensor-1.6.dist-info/WHEEL
adidas_sensor-1.6.dist-info/entry_points.txt
adidas_sensor-1.6.dist-info/top_level.txt
adidas_sensor-1.6.dist-info/RECORD
