Metadata-Version: 2.1
Name: adidas-sensor
Version: 1.6
Summary: Adidas Sensor Tool
Home-page: UNKNOWN
Author: Real Python
Author-email: office@realpython.com
License: MIT
Platform: UNKNOWN
Requires-Dist: numpy (>=1.15.4)
Requires-Dist: matplotlib (>=3.0.2)
Requires-Dist: pandas (>=0.23.4)
